laserembeddings/__init__.py
laserembeddings/__main__.py
laserembeddings/data/.gitkeep
laserembeddings/embedding.py
laserembeddings/encoder.py
laserembeddings/laser.py
laserembeddings/preprocessing.py
laserembeddings/utils.py
laserembeddings-1.1.2.dist-info/LICENSE
laserembeddings-1.1.2.dist-info/WHEEL
laserembeddings-1.1.2.dist-info/METADATA
laserembeddings-1.1.2.dist-info/RECORD
