Metadata-Version: 2.1
Name: laserembeddings
Version: 1.1.2
Summary: Production-ready LASER multilingual embeddings
Home-page: https://github.com/yannvgn/laserembeddings
License: BSD-3-Clause
Author: yannvgn
Author-email: hi@yannvgn.io
Requires-Python: >=3.6.2,<4.0.0
Classifier: License :: OSI Approved :: BSD License
Classifier: Programming Language :: Python :: 3
Classifier: Programming Language :: Python :: 3.10
Classifier: Programming Language :: Python :: 3.7
Classifier: Programming Language :: Python :: 3.8
Classifier: Programming Language :: Python :: 3.9
Provides-Extra: ja
Provides-Extra: zh
Requires-Dist: ipadic (==1.0.0); extra == "ja"
Requires-Dist: jieba (>=0.42.1,<0.43.0); extra == "zh"
Requires-Dist: mecab-python3 (>=1.0.1,<2.0.0); extra == "ja"
Requires-Dist: numpy (>=1.15.4,<2.0.0)
Requires-Dist: sacremoses (==0.0.35)
Requires-Dist: subword-nmt (>=0.3.6,<0.4.0)
Requires-Dist: torch (>=1.0.1.post2,<2.0.0)
Requires-Dist: transliterate (==1.10.2)
Project-URL: Repository, https://github.com/yannvgn/laserembeddings
